{"id": "s357", "group": "پادشاهی گشتاسپ صد و بیست سال بود", "num": 357, "title": "به خواب دیدن فردوسی دقیقی را", "stanzas": [{"lines": ["s357-l1", "s357-l2"]}, {"lines": ["s357-l3", "s357-l4"]}, {"lines": ["s357-l5", "s357-l6"]}, {"lines": ["s357-l7", "s357-l8"]}, {"lines": ["s357-l9", "s357-l10"]}, {"lines": ["s357-l11", "s357-l12"]}, {"lines": ["s357-l13", "s357-l14"]}, {"lines": ["s357-l15", "s357-l16"]}, {"lines": ["s357-l17", "s357-l18"]}, {"lines": ["s357-l19", "s357-l20"]}, {"lines": ["s357-l21", "s357-l22"]}, {"lines": ["s357-l23", "s357-l24"]}, {"lines": ["s357-l25", "s357-l26"]}], "lines": {"s357-l1": {"text": "چنان دید گوینده یک شب به خواب", "sids": ["s357-s1"], "tokens": [{"s": 0, "e": 4, "surface": "چنان", "lemma": "چنان", "pos": "NOUN", "seg": "s357-g1", "sid": "s357-s1"}, {"s": 5, "e": 8, "surface": "دید", "lemma": "دید", "pos": "NOUN", "seg": "s357-g1", "sid": "s357-s1"}, {"s": 9, "e": 15, "surface": "گوینده", "lemma": "گوینده", "pos": "NOUN", "seg": "s357-g1", "sid": "s357-s1"}, {"s": 16, "e": 18, "surface": "یک", "lemma": "یک", "pos": "NUM", "seg": "s357-g1", "sid": "s357-s1"}, {"s": 19, "e": 21, "surface": "شب", "lemma": "شب", "pos": "NOUN", "seg": "s357-g1", "sid": "s357-s1"}, {"s": 22, "e": 24, "surface": "به", "lemma": "به", "pos": "NOUN", "seg": "s357-g1", "sid": "s357-s1"}, {"s": 25, "e": 29, "surface": "خواب", "lemma": "خواب", "pos": "NOUN", "seg": "s357-g1", "sid": "s357-s1"}]}, "s357-l2": {"text": "که یک جام می‌داشتی چون گلاب", "sids": ["s357-s1"], "tokens": [{"s": 0, "e": 2, "surface": "که", "lemma": "که", "pos": "NOUN", "seg": "s357-g2", "sid": "s357-s1"}, {"s": 3, "e": 5, "surface": "یک", "lemma": "یک", "pos": "NUM", "seg": "s357-g2", "sid": "s357-s1"}, {"s": 6, "e": 9, "surface": "جام", "lemma": "جام", "pos": "NOUN", "seg": "s357-g2", "sid": "s357-s1"}, {"s": 10, "e": 18, "surface": "می‌داشتی", "lemma": "داشت#دار", "pos": "NOUN", "seg": "s357-g2", "sid": "s357-s1"}, {"s": 19, "e": 22, "surface": "چون", "lemma": "چون", "pos": "NOUN", "seg": "s357-g2", "sid": "s357-s1"}, {"s": 23, "e": 27, "surface": "گلاب", "lemma": "گلاب", "pos": "NOUN", "seg": "s357-g2", "sid": "s357-s1"}]}, "s357-l3": {"text": "دقیقی ز جایی پدید آمدی", "sids": ["s357-s2"], "tokens": [{"s": 0, "e": 5, "surface": "دقیقی", "lemma": "دقیقی", "pos": "NOUN", "seg": "s357-g3", "sid": "s357-s2"}, {"s": 6, "e": 7, "surface": "ز", "lemma": "ز", "pos": "NOUN", "seg": "s357-g3", "sid": "s357-s2"}, {"s": 8, "e": 12, "surface": "جایی", "lemma": "جایی", "pos": "NOUN", "seg": "s357-g3", "sid": "s357-s2"}, {"s": 13, "e": 17, "surface": "پدید", "lemma": "پدید", "pos": "NOUN", "seg": "s357-g3", "sid": "s357-s2"}, {"s": 18, "e": 22, "surface": "آمدی", "lemma": "آمد#آ", "pos": "NOUN", "seg": "s357-g3", "sid": "s357-s2"}]}, "s357-l4": {"text": "بران جام می‌داستانها زدی", "sids": ["s357-s2"], "tokens": [{"s": 0, "e": 4, "surface": "بران", "lemma": "بران", "pos": "NOUN", "seg": "s357-g4", "sid": "s357-s2"}, {"s": 5, "e": 8, "surface": "جام", "lemma": "جام", "pos": "NOUN", "seg": "s357-g4", "sid": "s357-s2"}, {"s": 9, "e": 20, "surface": "می‌داستانها", "lemma": "می‌داستانها", "pos": "NOUN", "seg": "s357-g4", "sid": "s357-s2"}, {"s": 21, "e": 24, "surface": "زدی", "lemma": "زد#زن", "pos": "NOUN", "seg": "s357-g4", "sid": "s357-s2"}]}, "s357-l5": {"text": "به فردوسی آواز دادی که می", "sids": ["s357-s3"], "tokens": [{"s": 0, "e": 2, "surface": "به", "lemma": "به", "pos": "NOUN", "seg": "s357-g5", "sid": "s357-s3"}, {"s": 3, "e": 9, "surface": "فردوسی", "lemma": "فردوسی", "pos": "NOUN", "seg": "s357-g5", "sid": "s357-s3"}, {"s": 10, "e": 14, "surface": "آواز", "lemma": "آواز", "pos": "NOUN", "seg": "s357-g5", "sid": "s357-s3"}, {"s": 15, "e": 19, "surface": "دادی", "lemma": "داد#ده", "pos": "NOUN", "seg": "s357-g5", "sid": "s357-s3"}, {"s": 20, "e": 22, "surface": "که", "lemma": "که", "pos": "NOUN", "seg": "s357-g5", "sid": "s357-s3"}, {"s": 23, "e": 25, "surface": "می", "lemma": "می", "pos": "NOUN", "seg": "s357-g5", "sid": "s357-s3"}]}, "s357-l6": {"text": "مخور جز بر آیین کاوس کی", "sids": ["s357-s3"], "tokens": [{"s": 0, "e": 4, "surface": "مخور", "lemma": "مخور", "pos": "NOUN", "seg": "s357-g6", "sid": "s357-s3"}, {"s": 5, "e": 7, "surface": "جز", "lemma": "جز", "pos": "NOUN", "seg": "s357-g6", "sid": "s357-s3"}, {"s": 8, "e": 10, "surface": "بر", "lemma": "بر", "pos": "NOUN", "seg": "s357-g6", "sid": "s357-s3"}, {"s": 11, "e": 15, "surface": "آیین", "lemma": "آیین", "pos": "NOUN", "seg": "s357-g6", "sid": "s357-s3"}, {"s": 16, "e": 20, "surface": "کاوس", "lemma": "کاوس", "pos": "NOUN", "seg": "s357-g6", "sid": "s357-s3"}, {"s": 21, "e": 23, "surface": "کی", "lemma": "کی", "pos": "NOUN", "seg": "s357-g6", "sid": "s357-s3"}]}, "s357-l7": {"text": "که شاهی ز گیتی گزیدی که بخت", "sids": ["s357-s4"], "tokens": [{"s": 0, "e": 2, "surface": "که", "lemma": "که", "pos": "NOUN", "seg": "s357-g7", "sid": "s357-s4"}, {"s": 3, "e": 7, "surface": "شاهی", "lemma": "شاهی", "pos": "NOUN", "seg": "s357-g7", "sid": "s357-s4"}, {"s": 8, "e": 9, "surface": "ز", "lemma": "ز", "pos": "NOUN", "seg": "s357-g7", "sid": "s357-s4"}, {"s": 10, "e": 14, "surface": "گیتی", "lemma": "گیتی", "pos": "NOUN", "seg": "s357-g7", "sid": "s357-s4"}, {"s": 15, "e": 20, "surface": "گزیدی", "lemma": "گزید#گز", "pos": "NOUN", "seg": "s357-g7", "sid": "s357-s4"}, {"s": 21, "e": 23, "surface": "که", "lemma": "که", "pos": "NOUN", "seg": "s357-g7", "sid": "s357-s4"}, {"s": 24, "e": 27, "surface": "بخت", "lemma": "بخت", "pos": "NOUN", "seg": "s357-g7", "sid": "s357-s4"}]}, "s357-l8": {"text": "بدو نازد و لشگر و تاج و تخت", "sids": ["s357-s4"], "tokens": [{"s": 0, "e": 3, "surface": "بدو", "lemma": "بدو", "pos": "NOUN", "seg": "s357-g8", "sid": "s357-s4"}, {"s": 4, "e": 8, "surface": "نازد", "lemma": "نازید#ناز", "pos": "NOUN", "seg": "s357-g8", "sid": "s357-s4"}, {"s": 9, "e": 10, "surface": "و", "lemma": "و", "pos": "NOUN", "seg": "s357-g8", "sid": "s357-s4"}, {"s": 11, "e": 15, "surface": "لشگر", "lemma": "لشگر", "pos": "NOUN", "seg": "s357-g8", "sid": "s357-s4"}, {"s": 16, "e": 17, "surface": "و", "lemma": "و", "pos": "NOUN", "seg": "s357-g8", "sid": "s357-s4"}, {"s": 18, "e": 21, "surface": "تاج", "lemma": "تاج", "pos": "NOUN", "seg": "s357-g8", "sid": "s357-s4"}, {"s": 22, "e": 23, "surface": "و", "lemma": "و", "pos": "NOUN", "seg": "s357-g8", "sid": "s357-s4"}, {"s": 24, "e": 27, "surface": "تخت", "lemma": "تخت", "pos": "NOUN", "seg": "s357-g8", "sid": "s357-s4"}]}, "s357-l9": {"text": "شهنشاه محمود گیرنده شهر", "sids": ["s357-s5"], "tokens": [{"s": 0, "e": 6, "surface": "شهنشاه", "lemma": "شهنشاه", "pos": "NOUN", "seg": "s357-g9", "sid": "s357-s5"}, {"s": 7, "e": 12, "surface": "محمود", "lemma": "محمود", "pos": "NOUN", "seg": "s357-g9", "sid": "s357-s5"}, {"s": 13, "e": 19, "surface": "گیرنده", "lemma": "گیرنده", "pos": "NOUN", "seg": "s357-g9", "sid": "s357-s5"}, {"s": 20, "e": 23, "surface": "شهر", "lemma": "شهر", "pos": "NOUN", "seg": "s357-g9", "sid": "s357-s5"}]}, "s357-l10": {"text": "ز شادی به هر کس رسانیده بهر", "sids": ["s357-s5"], "tokens": [{"s": 0, "e": 1, "surface": "ز", "lemma": "ز", "pos": "NOUN", "seg": "s357-g10", "sid": "s357-s5"}, {"s": 2, "e": 6, "surface": "شادی", "lemma": "شادی", "pos": "NOUN", "seg": "s357-g10", "sid": "s357-s5"}, {"s": 7, "e": 9, "surface": "به", "lemma": "به", "pos": "NOUN", "seg": "s357-g10", "sid": "s357-s5"}, {"s": 10, "e": 12, "surface": "هر", "lemma": "هر", "pos": "NOUN", "seg": "s357-g10", "sid": "s357-s5"}, {"s": 13, "e": 15, "surface": "کس", "lemma": "کس", "pos": "NOUN", "seg": "s357-g10", "sid": "s357-s5"}, {"s": 16, "e": 23, "surface": "رسانیده", "lemma": "رسانیده", "pos": "NOUN", "seg": "s357-g10", "sid": "s357-s5"}, {"s": 24, "e": 27, "surface": "بهر", "lemma": "بهر", "pos": "NOUN", "seg": "s357-g10", "sid": "s357-s5"}]}, "s357-l11": {"text": "از امروز تا سال هشتاد و پنج", "sids": ["s357-s6"], "tokens": [{"s": 0, "e": 2, "surface": "از", "lemma": "از", "pos": "NOUN", "seg": "s357-g11", "sid": "s357-s6"}, {"s": 3, "e": 8, "surface": "امروز", "lemma": "امروز", "pos": "NOUN", "seg": "s357-g11", "sid": "s357-s6"}, {"s": 9, "e": 11, "surface": "تا", "lemma": "تا", "pos": "NOUN", "seg": "s357-g11", "sid": "s357-s6"}, {"s": 12, "e": 15, "surface": "سال", "lemma": "سال", "pos": "NOUN", "seg": "s357-g11", "sid": "s357-s6"}, {"s": 16, "e": 21, "surface": "هشتاد", "lemma": "هشتاد", "pos": "NUM", "seg": "s357-g11", "sid": "s357-s6"}, {"s": 22, "e": 23, "surface": "و", "lemma": "و", "pos": "NOUN", "seg": "s357-g11", "sid": "s357-s6"}, {"s": 24, "e": 27, "surface": "پنج", "lemma": "پنج", "pos": "NUM", "seg": "s357-g11", "sid": "s357-s6"}]}, "s357-l12": {"text": "بکاهدش رنج و نکاهدش گنج", "sids": ["s357-s6"], "tokens": [{"s": 0, "e": 6, "surface": "بکاهدش", "lemma": "بکاهدش", "pos": "NOUN", "seg": "s357-g12", "sid": "s357-s6"}, {"s": 7, "e": 10, "surface": "رنج", "lemma": "رنج", "pos": "NOUN", "seg": "s357-g12", "sid": "s357-s6"}, {"s": 11, "e": 12, "surface": "و", "lemma": "و", "pos": "NOUN", "seg": "s357-g12", "sid": "s357-s6"}, {"s": 13, "e": 19, "surface": "نکاهدش", "lemma": "نکاهدش", "pos": "NOUN", "seg": "s357-g12", "sid": "s357-s6"}, {"s": 20, "e": 23, "surface": "گنج", "lemma": "گنج", "pos": "NOUN", "seg": "s357-g12", "sid": "s357-s6"}]}, "s357-l13": {"text": "ازین پس به چین اندر آرد سپاه", "sids": ["s357-s7"], "tokens": [{"s": 0, "e": 2, "surface": "از", "lemma": "از", "pos": "NOUN", "seg": "s357-g13", "sid": "s357-s7"}, {"s": 2, "e": 4, "surface": "ین", "lemma": "ین", "pos": "NOUN", "seg": "s357-g13", "sid": "s357-s7"}, {"s": 5, "e": 7, "surface": "پس", "lemma": "پس", "pos": "NOUN", "seg": "s357-g13", "sid": "s357-s7"}, {"s": 8, "e": 10, "surface": "به", "lemma": "به", "pos": "NOUN", "seg": "s357-g13", "sid": "s357-s7"}, {"s": 11, "e": 14, "surface": "چین", "lemma": "چین", "pos": "NOUN", "seg": "s357-g13", "sid": "s357-s7"}, {"s": 15, "e": 19, "surface": "اندر", "lemma": "اندر", "pos": "NOUN", "seg": "s357-g13", "sid": "s357-s7"}, {"s": 20, "e": 23, "surface": "آرد", "lemma": "آرد", "pos": "NOUN", "seg": "s357-g13", "sid": "s357-s7"}, {"s": 24, "e": 28, "surface": "سپاه", "lemma": "سپاه", "pos": "NOUN", "seg": "s357-g13", "sid": "s357-s7"}]}, "s357-l14": {"text": "همه مهتران برگشایند راه", "sids": ["s357-s7"], "tokens": [{"s": 0, "e": 3, "surface": "همه", "lemma": "همه", "pos": "NOUN", "seg": "s357-g14", "sid": "s357-s7"}, {"s": 4, "e": 10, "surface": "مهتران", "lemma": "مه", "pos": "NOUN", "seg": "s357-g14", "sid": "s357-s7"}, {"s": 11, "e": 19, "surface": "برگشایند", "lemma": "برگشایند", "pos": "NOUN", "seg": "s357-g14", "sid": "s357-s7"}, {"s": 20, "e": 23, "surface": "راه", "lemma": "راه", "pos": "NOUN", "seg": "s357-g14", "sid": "s357-s7"}]}, "s357-l15": {"text": "نبایدش گفتن کسی را درشت", "sids": ["s357-s8"], "tokens": [{"s": 0, "e": 6, "surface": "نبایدش", "lemma": "نباید", "pos": "NOUN", "seg": "s357-g15", "sid": "s357-s8"}, {"s": 7, "e": 11, "surface": "گفتن", "lemma": "گفتن", "pos": "NOUN", "seg": "s357-g15", "sid": "s357-s8"}, {"s": 12, "e": 15, "surface": "کسی", "lemma": "کسی", "pos": "NOUN", "seg": "s357-g15", "sid": "s357-s8"}, {"s": 16, "e": 18, "surface": "را", "lemma": "را", "pos": "NOUN", "seg": "s357-g15", "sid": "s357-s8"}, {"s": 19, "e": 23, "surface": "درشت", "lemma": "درشت", "pos": "NOUN", "seg": "s357-g15", "sid": "s357-s8"}]}, "s357-l16": {"text": "همه تاج شاهانش آمد به مشت", "sids": ["s357-s8"], "tokens": [{"s": 0, "e": 3, "surface": "همه", "lemma": "همه", "pos": "NOUN", "seg": "s357-g16", "sid": "s357-s8"}, {"s": 4, "e": 7, "surface": "تاج", "lemma": "تاج", "pos": "NOUN", "seg": "s357-g16", "sid": "s357-s8"}, {"s": 8, "e": 14, "surface": "شاهانش", "lemma": "شاهانش", "pos": "NOUN", "seg": "s357-g16", "sid": "s357-s8"}, {"s": 15, "e": 18, "surface": "آمد", "lemma": "آمد#آ", "pos": "NOUN", "seg": "s357-g16", "sid": "s357-s8"}, {"s": 19, "e": 21, "surface": "به", "lemma": "به", "pos": "NOUN", "seg": "s357-g16", "sid": "s357-s8"}, {"s": 22, "e": 25, "surface": "مشت", "lemma": "مشت", "pos": "NOUN", "seg": "s357-g16", "sid": "s357-s8"}]}, "s357-l17": {"text": "بدین نامه‌گر چند بشتافتی", "sids": ["s357-s9"], "tokens": [{"s": 0, "e": 1, "surface": "ب", "lemma": "ب", "pos": "NOUN", "seg": "s357-g17", "sid": "s357-s9"}, {"s": 1, "e": 4, "surface": "دین", "lemma": "دین", "pos": "NOUN", "seg": "s357-g17", "sid": "s357-s9"}, {"s": 5, "e": 12, "surface": "نامه‌گر", "lemma": "نامه‌گر", "pos": "NOUN", "seg": "s357-g17", "sid": "s357-s9"}, {"s": 13, "e": 16, "surface": "چند", "lemma": "چند", "pos": "NOUN", "seg": "s357-g17", "sid": "s357-s9"}, {"s": 17, "e": 24, "surface": "بشتافتی", "lemma": "بشتافتی", "pos": "NOUN", "seg": "s357-g17", "sid": "s357-s9"}]}, "s357-l18": {"text": "کنون هرچ جستی همه یافتی", "sids": ["s357-s9"], "tokens": [{"s": 0, "e": 4, "surface": "کنون", "lemma": "کنون", "pos": "NOUN", "seg": "s357-g18", "sid": "s357-s9"}, {"s": 5, "e": 8, "surface": "هرچ", "lemma": "هرچ", "pos": "NOUN", "seg": "s357-g18", "sid": "s357-s9"}, {"s": 9, "e": 13, "surface": "جستی", "lemma": "جست#جه", "pos": "NOUN", "seg": "s357-g18", "sid": "s357-s9"}, {"s": 14, "e": 17, "surface": "همه", "lemma": "همه", "pos": "NOUN", "seg": "s357-g18", "sid": "s357-s9"}, {"s": 18, "e": 23, "surface": "یافتی", "lemma": "یافت#یاب", "pos": "NOUN", "seg": "s357-g18", "sid": "s357-s9"}]}, "s357-l19": {"text": "ازین باره من پیش گفتم سخن", "sids": ["s357-s10"], "tokens": [{"s": 0, "e": 2, "surface": "از", "lemma": "از", "pos": "NOUN", "seg": "s357-g19", "sid": "s357-s10"}, {"s": 2, "e": 4, "surface": "ین", "lemma": "ین", "pos": "NOUN", "seg": "s357-g19", "sid": "s357-s10"}, {"s": 5, "e": 9, "surface": "باره", "lemma": "باره", "pos": "NOUN", "seg": "s357-g19", "sid": "s357-s10"}, {"s": 10, "e": 12, "surface": "من", "lemma": "من", "pos": "NOUN", "seg": "s357-g19", "sid": "s357-s10"}, {"s": 13, "e": 16, "surface": "پیش", "lemma": "پیش", "pos": "NOUN", "seg": "s357-g19", "sid": "s357-s10"}, {"s": 17, "e": 21, "surface": "گفتم", "lemma": "گفت#گو", "pos": "NOUN", "seg": "s357-g19", "sid": "s357-s10"}, {"s": 22, "e": 25, "surface": "سخن", "lemma": "سخن", "pos": "NOUN", "seg": "s357-g19", "sid": "s357-s10"}]}, "s357-l20": {"text": "سخن را نیامد سراسر به بن", "sids": ["s357-s10"], "tokens": [{"s": 0, "e": 3, "surface": "سخن", "lemma": "سخن", "pos": "NOUN", "seg": "s357-g20", "sid": "s357-s10"}, {"s": 4, "e": 6, "surface": "را", "lemma": "را", "pos": "NOUN", "seg": "s357-g20", "sid": "s357-s10"}, {"s": 7, "e": 12, "surface": "نیامد", "lemma": "نیامد", "pos": "NOUN", "seg": "s357-g20", "sid": "s357-s10"}, {"s": 13, "e": 18, "surface": "سراسر", "lemma": "سراسر", "pos": "NOUN", "seg": "s357-g20", "sid": "s357-s10"}, {"s": 19, "e": 21, "surface": "به", "lemma": "به", "pos": "NOUN", "seg": "s357-g20", "sid": "s357-s10"}, {"s": 22, "e": 24, "surface": "بن", "lemma": "بن", "pos": "NOUN", "seg": "s357-g20", "sid": "s357-s10"}]}, "s357-l21": {"text": "ز گشتاسپ و ارجاسپ بیتی هزار", "sids": ["s357-s11"], "tokens": [{"s": 0, "e": 1, "surface": "ز", "lemma": "ز", "pos": "NOUN", "seg": "s357-g21", "sid": "s357-s11"}, {"s": 2, "e": 8, "surface": "گشتاسپ", "lemma": "گشتاسپ", "pos": "NOUN", "seg": "s357-g21", "sid": "s357-s11"}, {"s": 9, "e": 10, "surface": "و", "lemma": "و", "pos": "NOUN", "seg": "s357-g21", "sid": "s357-s11"}, {"s": 11, "e": 17, "surface": "ارجاسپ", "lemma": "ارجاسپ", "pos": "NOUN", "seg": "s357-g21", "sid": "s357-s11"}, {"s": 18, "e": 22, "surface": "بیتی", "lemma": "بیتی", "pos": "NOUN", "seg": "s357-g21", "sid": "s357-s11"}, {"s": 23, "e": 27, "surface": "هزار", "lemma": "هزار", "pos": "NUM", "seg": "s357-g21", "sid": "s357-s11"}]}, "s357-l22": {"text": "بگفتم سرآمد مرا روزگار", "sids": ["s357-s11"], "tokens": [{"s": 0, "e": 5, "surface": "بگفتم", "lemma": "بگفتم", "pos": "NOUN", "seg": "s357-g22", "sid": "s357-s11"}, {"s": 6, "e": 11, "surface": "سرآمد", "lemma": "سرآمد", "pos": "NOUN", "seg": "s357-g22", "sid": "s357-s11"}, {"s": 12, "e": 13, "surface": "م", "lemma": "#هست", "pos": "NOUN", "seg": "s357-g22", "sid": "s357-s11"}, {"s": 13, "e": 15, "surface": "را", "lemma": "را", "pos": "NOUN", "seg": "s357-g22", "sid": "s357-s11"}, {"s": 16, "e": 22, "surface": "روزگار", "lemma": "روزگار", "pos": "NOUN", "seg": "s357-g22", "sid": "s357-s11"}]}, "s357-l23": {"text": "گر آن مایه نزد شهنشه رسد", "sids": ["s357-s12"], "tokens": [{"s": 0, "e": 2, "surface": "گر", "lemma": "گر", "pos": "NOUN", "seg": "s357-g23", "sid": "s357-s12"}, {"s": 3, "e": 5, "surface": "آن", "lemma": "آن", "pos": "NOUN", "seg": "s357-g23", "sid": "s357-s12"}, {"s": 6, "e": 10, "surface": "مایه", "lemma": "مایه", "pos": "NOUN", "seg": "s357-g23", "sid": "s357-s12"}, {"s": 11, "e": 14, "surface": "نزد", "lemma": "نزد", "pos": "NOUN", "seg": "s357-g23", "sid": "s357-s12"}, {"s": 15, "e": 20, "surface": "شهنشه", "lemma": "شهنشه", "pos": "NOUN", "seg": "s357-g23", "sid": "s357-s12"}, {"s": 21, "e": 24, "surface": "رسد", "lemma": "رسید#رس", "pos": "NOUN", "seg": "s357-g23", "sid": "s357-s12"}]}, "s357-l24": {"text": "روان من از خاک بر مه رسد", "sids": ["s357-s12"], "tokens": [{"s": 0, "e": 4, "surface": "روان", "lemma": "روان", "pos": "NOUN", "seg": "s357-g24", "sid": "s357-s12"}, {"s": 5, "e": 7, "surface": "من", "lemma": "من", "pos": "NOUN", "seg": "s357-g24", "sid": "s357-s12"}, {"s": 8, "e": 10, "surface": "از", "lemma": "از", "pos": "NOUN", "seg": "s357-g24", "sid": "s357-s12"}, {"s": 11, "e": 14, "surface": "خاک", "lemma": "خاک", "pos": "NOUN", "seg": "s357-g24", "sid": "s357-s12"}, {"s": 15, "e": 17, "surface": "بر", "lemma": "بر", "pos": "NOUN", "seg": "s357-g24", "sid": "s357-s12"}, {"s": 18, "e": 20, "surface": "مه", "lemma": "مه", "pos": "NOUN", "seg": "s357-g24", "sid": "s357-s12"}, {"s": 21, "e": 24, "surface": "رسد", "lemma": "رسید#رس", "pos": "NOUN", "seg": "s357-g24", "sid": "s357-s12"}]}, "s357-l25": {"text": "کنون من بگویم سخن کو بگفت", "sids": ["s357-s13"], "tokens": [{"s": 0, "e": 4, "surface": "کنون", "lemma": "کنون", "pos": "NOUN", "seg": "s357-g25", "sid": "s357-s13"}, {"s": 5, "e": 7, "surface": "من", "lemma": "من", "pos": "NOUN", "seg": "s357-g25", "sid": "s357-s13"}, {"s": 8, "e": 13, "surface": "بگویم", "lemma": "گفت#گو", "pos": "NOUN", "seg": "s357-g25", "sid": "s357-s13"}, {"s": 14, "e": 17, "surface": "سخن", "lemma": "سخن", "pos": "NOUN", "seg": "s357-g25", "sid": "s357-s13"}, {"s": 18, "e": 20, "surface": "کو", "lemma": "کو", "pos": "NOUN", "seg": "s357-g25", "sid": "s357-s13"}, {"s": 21, "e": 25, "surface": "بگفت", "lemma": "بگفت", "pos": "NOUN", "seg": "s357-g25", "sid": "s357-s13"}]}, "s357-l26": {"text": "منم زنده او گشت با خاک جفت", "sids": ["s357-s13"], "tokens": [{"s": 0, "e": 3, "surface": "منم", "lemma": "منم", "pos": "NOUN", "seg": "s357-g26", "sid": "s357-s13"}, {"s": 4, "e": 8, "surface": "زنده", "lemma": "زنده", "pos": "NOUN", "seg": "s357-g26", "sid": "s357-s13"}, {"s": 9, "e": 11, "surface": "او", "lemma": "او", "pos": "NOUN", "seg": "s357-g26", "sid": "s357-s13"}, {"s": 12, "e": 15, "surface": "گشت", "lemma": "گشت", "pos": "NOUN", "seg": "s357-g26", "sid": "s357-s13"}, {"s": 16, "e": 18, "surface": "با", "lemma": "با", "pos": "NOUN", "seg": "s357-g26", "sid": "s357-s13"}, {"s": 19, "e": 22, "surface": "خاک", "lemma": "خاک", "pos": "NOUN", "seg": "s357-g26", "sid": "s357-s13"}, {"s": 23, "e": 26, "surface": "جفت", "lemma": "جفت", "pos": "NOUN", "seg": "s357-g26", "sid": "s357-s13"}]}}, "sentences": {"s357-s1": {"text": "چنان دید گوینده یک شب به خواب که یک جام می‌داشتی چون گلاب", "lines": ["s357-l1", "s357-l2"], "segs": ["s357-g1", "s357-g2"]}, "s357-s2": {"text": "دقیقی ز جایی پدید آمدی بران جام می‌داستانها زدی", "lines": ["s357-l3", "s357-l4"], "segs": ["s357-g3", "s357-g4"]}, "s357-s3": {"text": "به فردوسی آواز دادی که می مخور جز بر آیین کاوس کی", "lines": ["s357-l5", "s357-l6"], "segs": ["s357-g5", "s357-g6"]}, "s357-s4": {"text": "که شاهی ز گیتی گزیدی که بخت بدو نازد و لشگر و تاج و تخت", "lines": ["s357-l7", "s357-l8"], "segs": ["s357-g7", "s357-g8"]}, "s357-s5": {"text": "شهنشاه محمود گیرنده شهر ز شادی به هر کس رسانیده بهر", "lines": ["s357-l9", "s357-l10"], "segs": ["s357-g9", "s357-g10"]}, "s357-s6": {"text": "از امروز تا سال هشتاد و پنج بکاهدش رنج و نکاهدش گنج", "lines": ["s357-l11", "s357-l12"], "segs": ["s357-g11", "s357-g12"]}, "s357-s7": {"text": "ازین پس به چین اندر آرد سپاه همه مهتران برگشایند راه", "lines": ["s357-l13", "s357-l14"], "segs": ["s357-g13", "s357-g14"]}, "s357-s8": {"text": "نبایدش گفتن کسی را درشت همه تاج شاهانش آمد به مشت", "lines": ["s357-l15", "s357-l16"], "segs": ["s357-g15", "s357-g16"]}, "s357-s9": {"text": "بدین نامه‌گر چند بشتافتی کنون هرچ جستی همه یافتی", "lines": ["s357-l17", "s357-l18"], "segs": ["s357-g17", "s357-g18"]}, "s357-s10": {"text": "ازین باره من پیش گفتم سخن سخن را نیامد سراسر به بن", "lines": ["s357-l19", "s357-l20"], "segs": ["s357-g19", "s357-g20"]}, "s357-s11": {"text": "ز گشتاسپ و ارجاسپ بیتی هزار بگفتم سرآمد مرا روزگار", "lines": ["s357-l21", "s357-l22"], "segs": ["s357-g21", "s357-g22"]}, "s357-s12": {"text": "گر آن مایه نزد شهنشه رسد روان من از خاک بر مه رسد", "lines": ["s357-l23", "s357-l24"], "segs": ["s357-g23", "s357-g24"]}, "s357-s13": {"text": "کنون من بگویم سخن کو بگفت منم زنده او گشت با خاک جفت", "lines": ["s357-l25", "s357-l26"], "segs": ["s357-g25", "s357-g26"]}}, "segments": {"s357-g1": {"text": "چنان دید گوینده یک شب به خواب", "sid": "s357-s1", "lines": ["s357-l1"]}, "s357-g2": {"text": "که یک جام می‌داشتی چون گلاب", "sid": "s357-s1", "lines": ["s357-l2"]}, "s357-g3": {"text": "دقیقی ز جایی پدید آمدی", "sid": "s357-s2", "lines": ["s357-l3"]}, "s357-g4": {"text": "بران جام می‌داستانها زدی", "sid": "s357-s2", "lines": ["s357-l4"]}, "s357-g5": {"text": "به فردوسی آواز دادی که می", "sid": "s357-s3", "lines": ["s357-l5"]}, "s357-g6": {"text": "مخور جز بر آیین کاوس کی", "sid": "s357-s3", "lines": ["s357-l6"]}, "s357-g7": {"text": "که شاهی ز گیتی گزیدی که بخت", "sid": "s357-s4", "lines": ["s357-l7"]}, "s357-g8": {"text": "بدو نازد و لشگر و تاج و تخت", "sid": "s357-s4", "lines": ["s357-l8"]}, "s357-g9": {"text": "شهنشاه محمود گیرنده شهر", "sid": "s357-s5", "lines": ["s357-l9"]}, "s357-g10": {"text": "ز شادی به هر کس رسانیده بهر", "sid": "s357-s5", "lines": ["s357-l10"]}, "s357-g11": {"text": "از امروز تا سال هشتاد و پنج", "sid": "s357-s6", "lines": ["s357-l11"]}, "s357-g12": {"text": "بکاهدش رنج و نکاهدش گنج", "sid": "s357-s6", "lines": ["s357-l12"]}, "s357-g13": {"text": "ازین پس به چین اندر آرد سپاه", "sid": "s357-s7", "lines": ["s357-l13"]}, "s357-g14": {"text": "همه مهتران برگشایند راه", "sid": "s357-s7", "lines": ["s357-l14"]}, "s357-g15": {"text": "نبایدش گفتن کسی را درشت", "sid": "s357-s8", "lines": ["s357-l15"]}, "s357-g16": {"text": "همه تاج شاهانش آمد به مشت", "sid": "s357-s8", "lines": ["s357-l16"]}, "s357-g17": {"text": "بدین نامه‌گر چند بشتافتی", "sid": "s357-s9", "lines": ["s357-l17"]}, "s357-g18": {"text": "کنون هرچ جستی همه یافتی", "sid": "s357-s9", "lines": ["s357-l18"]}, "s357-g19": {"text": "ازین باره من پیش گفتم سخن", "sid": "s357-s10", "lines": ["s357-l19"]}, "s357-g20": {"text": "سخن را نیامد سراسر به بن", "sid": "s357-s10", "lines": ["s357-l20"]}, "s357-g21": {"text": "ز گشتاسپ و ارجاسپ بیتی هزار", "sid": "s357-s11", "lines": ["s357-l21"]}, "s357-g22": {"text": "بگفتم سرآمد مرا روزگار", "sid": "s357-s11", "lines": ["s357-l22"]}, "s357-g23": {"text": "گر آن مایه نزد شهنشه رسد", "sid": "s357-s12", "lines": ["s357-l23"]}, "s357-g24": {"text": "روان من از خاک بر مه رسد", "sid": "s357-s12", "lines": ["s357-l24"]}, "s357-g25": {"text": "کنون من بگویم سخن کو بگفت", "sid": "s357-s13", "lines": ["s357-l25"]}, "s357-g26": {"text": "منم زنده او گشت با خاک جفت", "sid": "s357-s13", "lines": ["s357-l26"]}}}